torch_mdct/__init__.py
torch_mdct/functional.py
torch_mdct/torch_mdct.py
torch_mdct/windows.py
torch_mdct-0.4.1.dist-info/METADATA
torch_mdct-0.4.1.dist-info/WHEEL
torch_mdct-0.4.1.dist-info/licenses/LICENSE
torch_mdct-0.4.1.dist-info/RECORD
