Metadata-Version: 2.4
Name: torch_mdct
Version: 0.4.1
Summary: A PyTorch implementation of the Modified Discrete Cosine Transform (MDCT) and its inverse for audio processing.
Project-URL: Homepage, https://github.com/Kinyugo/torch_mdct
Project-URL: Issues, https://github.com/Kinyugo/torch_mdct/issues
Author-email: Kinyugo Maina <kinyugomaina@gmail.com>
License-File: LICENSE
Keywords: audio,imdct,mdct,pytorch,signal processing
Classifier: License :: OSI Approved :: MIT License
Classifier: Operating System :: OS Independent
Classifier: Programming Language :: Python :: 3
Requires-Python: >=3.8
Requires-Dist: torch
Provides-Extra: notebook
Requires-Dist: ipython; extra == 'notebook'
Requires-Dist: matplotlib; extra == 'notebook'
